{
  "_comment": "Config para etrader_sample.xlsx - ajustar columnas según tu Excel real",
  "market": {
    "sheet": "Opciones",
    "start_row": 2,
    "end_row": 500,
    "columns": {
      "symbol": "A",
      "underlying": "B",
      "type": "C",
      "strike": "D",
      "expiration": "E",
      "last_price": "F",
      "bid": "G",
      "ask": "H",
      "volume": "I",
      "iv": "J",
      "open_interest": "K",
      "spot_price": "L"
    }
  },
  "portfolio": {
    "sheet": "Portfolio",
    "start_row": 2,
    "end_row": 50,
    "columns": {
      "symbol": "A",
      "quantity": "B",
      "entry_price": "C",
      "current_price": "D",
      "pnl": "E"
    }
  }
}
